marketplace_api/__init__.py
marketplace_api/oz_api.py
marketplace_api/utils.py
marketplace_api/wb_api.py
marketplace_api/ym_api.py
marketplace_api-0.0.3.dist-info/LICENSE
marketplace_api-0.0.3.dist-info/METADATA
marketplace_api-0.0.3.dist-info/WHEEL
marketplace_api-0.0.3.dist-info/RECORD
